{
  "guids": {
    "https://www.infoq.cn/article/3s5PXoP3xckCe80oVEeB": "2026-03-06T02:49:38.501Z",
    "https://www.infoq.cn/article/4QxbOWVR1c1CipCUI2Lk": "2026-03-06T02:49:38.501Z",
    "https://www.infoq.cn/article/58MqJzPWvi2Mtdu147Qv": "2026-03-09T03:13:58.488Z",
    "https://www.infoq.cn/article/5ydQqEFM2Kkskgyl0u3X": "2026-03-09T03:13:58.488Z",
    "https://www.infoq.cn/article/8uzPv9ggRNrgDLtb7ywE": "2026-03-09T03:13:58.488Z",
    "https://www.infoq.cn/article/AIVoC9eKfZhW199IQkwB": "2026-03-09T05:02:23.815Z",
    "https://www.infoq.cn/article/cYD3g1jMkc6D4RTuDfOc": "2026-03-07T05:50:31.376Z",
    "https://www.infoq.cn/article/djsCe3heSCRUEwBZtsvW": "2026-03-06T07:06:13.503Z",
    "https://www.infoq.cn/article/DO91JjU98lL2Z4CEGzWx": "2026-03-09T11:00:57.839Z",
    "https://www.infoq.cn/article/e2DdycRSttfZvU2ZkauH": "2026-03-09T03:13:58.488Z",
    "https://www.infoq.cn/article/Ea8hFxwccb3Q190l6pI2": "2026-03-06T02:49:38.501Z",
    "https://www.infoq.cn/article/eJaITDi1aTzpAR6wmZzz": "2026-03-07T02:43:07.952Z",
    "https://www.infoq.cn/article/i2uiflYNMtTwmxeVCTxp": "2026-03-06T04:50:41.088Z",
    "https://www.infoq.cn/article/IHiheIrpN1lo0jJJlqhD": "2026-03-09T03:13:58.488Z",
    "https://www.infoq.cn/article/ITsw8J6aX1q6XPsoDMsx": "2026-03-07T02:43:07.952Z",
    "https://www.infoq.cn/article/L8Ozfyk1Epmm2SpwWqDT": "2026-03-06T07:06:13.503Z",
    "https://www.infoq.cn/article/oRLbiZDv9maVQDk0swaR": "2026-03-09T03:13:58.488Z",
    "https://www.infoq.cn/article/oy5f04ZRYI2YRgD7p8y6": "2026-03-06T02:49:38.501Z",
    "https://www.infoq.cn/article/q2gYpu0ys425KtKuGCm5": "2026-03-08T03:10:56.859Z",
    "https://www.infoq.cn/article/qOpuZutTvaO9O1NcwFRc": "2026-03-06T08:54:38.389Z",
    "https://www.infoq.cn/article/rLVi30GAlEd0bX8VxTBZ": "2026-03-09T03:13:58.488Z",
    "https://www.infoq.cn/article/sRyWIACcuxPivTo8DwdA": "2026-03-08T03:10:56.859Z",
    "https://www.infoq.cn/article/TJ4K86cg0ilwKlZHuvxD": "2026-03-06T09:54:27.722Z",
    "https://www.infoq.cn/article/TtksmXyaNvO1LhACOzmp": "2026-03-06T11:41:31.067Z",
    "https://www.infoq.cn/article/TZ9h5JFJ5GZ92PL76yaD": "2026-03-07T10:39:04.880Z",
    "https://www.infoq.cn/article/UlSPN3tdkCRtgTkuN2q1": "2026-03-08T03:10:56.859Z",
    "https://www.infoq.cn/article/vhvC3K6BIR9dhJ1FVqK2": "2026-03-06T02:49:38.501Z",
    "https://www.infoq.cn/article/wZ6OLl08OyezbYDCLrQT": "2026-03-09T03:13:58.488Z",
    "https://www.infoq.cn/article/XiMNJ9e87lH8Xu9CpUHG": "2026-03-09T11:47:21.856Z",
    "https://www.infoq.cn/article/yB0DZ1c5uLDdkVsJvgWY": "2026-03-09T06:09:56.888Z",
    "https://www.infoq.cn/article/zVRRjI7EfCiEoYTS2QqH": "2026-03-09T10:04:57.833Z"
  },
  "updated_at": "2026-03-09T17:59:19.144Z"
}